exdc/_consts.py
exdc/client.py
exdc/exception.py
exdc-0.6.2.dist-info/COPYING.md
exdc-0.6.2.dist-info/METADATA
exdc-0.6.2.dist-info/WHEEL
exdc-0.6.2.dist-info/top_level.txt
exdc-0.6.2.dist-info/RECORD
