Metadata-Version: 2.1
Name: exdc
Version: 0.6.2
Summary: Discord Gateway & REST client
Home-page: https://github.com/eXhumer/pyeXDC
Author: eXhumer
Author-email: exhumer@exhumer.cc
License: AGPL-3.0-only
Classifier: Development Status :: 4 - Beta
Classifier: License :: OSI Approved :: GNU Affero General Public License v3
Classifier: Programming Language :: Python :: 3
Classifier: Programming Language :: Python :: 3.11
Requires-Python: >=3.11
License-File: COPYING.md
Requires-Dist: httpx
Requires-Dist: websocket-client
Provides-Extra: http2
Requires-Dist: httpx[http2] ; extra == 'http2'
